setup.py
myllmcli/__init__.py
myllmcli/version.py
myllmcli.egg-info/PKG-INFO
myllmcli.egg-info/SOURCES.txt
myllmcli.egg-info/dependency_links.txt
myllmcli.egg-info/entry_points.txt
myllmcli.egg-info/requires.txt
myllmcli.egg-info/top_level.txt
myllmcli/command/__init__.py
myllmcli/command/cli.py
myllmcli/command/model_download.py