Metadata-Version: 2.1
Name: myllmcli
Version: 0.0.1
Summary: llmcli 模型下载
Home-page: https://gitee.com/zhys513/myllmcli
Author: zhys513
Author-email: 254851907@qq.com
License: UNKNOWN
Platform: UNKNOWN
Requires-Python: >=3.6
